gridview/__init__.py
gridview/gridview.py
gridview-0.1.5.dist-info/LICENSE
gridview-0.1.5.dist-info/WHEEL
gridview-0.1.5.dist-info/METADATA
gridview-0.1.5.dist-info/RECORD
