Metadata-Version: 2.1
Name: gridview
Version: 0.1.5
Summary: Visualize your 2D iterable.
Home-page: https://gergelyk.github.io/python-gridview
License: MIT
Author: Grzegorz Krasoń
Author-email: grzegorz.krason@gmail.com
Requires-Python: >=3.8,<4.0
Classifier: License :: OSI Approved :: MIT License
Classifier: Programming Language :: Python :: 3
Classifier: Programming Language :: Python :: 3.10
Classifier: Programming Language :: Python :: 3.8
Classifier: Programming Language :: Python :: 3.9
Requires-Dist: svgwrite (>=1.4.1,<2.0.0)
Project-URL: Documentation, https://gergelyk.github.io/python-gridview
Project-URL: Repository, https://github.com/gergelyk/python-gridview
